README.md
setup.py
pyformationlib/__init__.py
pyformationlib/config.py
pyformationlib/constants.py
pyformationlib/exception.py
pyformationlib/network.py
pyformationlib/project.py
pyformationlib/ssh.py
pyformationlib/util.py
pyformationlib.egg-info/PKG-INFO
pyformationlib.egg-info/SOURCES.txt
pyformationlib.egg-info/dependency_links.txt
pyformationlib.egg-info/requires.txt
pyformationlib.egg-info/top_level.txt