Metadata-Version: 2.1
Name: pyformationlib
Version: 4.0.3
Summary: Couchbase Cloud Automation Library
Home-page: https://github.com/mminichino/couch-formation-lib
Author: Michael Minichino
Author-email: info@unix.us.com
License: Apache License 2.0
Keywords: couchbase,devops,automation
Classifier: Development Status :: 4 - Beta
Classifier: License :: OSI Approved :: Apache Software License
Classifier: Intended Audience :: Developers
Classifier: Operating System :: OS Independent
Classifier: Programming Language :: Python
Classifier: Programming Language :: Python :: 3
Classifier: Topic :: Database
Classifier: Topic :: Software Development :: Libraries
Classifier: Topic :: Software Development :: Libraries :: Python Modules
Requires-Python: >=3.8
